armada_sde/__init__.py
armada_sde/settings.py
armada_sde/urls.py
armada_sde/wsgi.py
armada_sde/management/__init__.py
armada_sde/management/commands/__init__.py
armada_sde/management/commands/pg_generate_models.py
armada_sde/management/commands/pg_import_sde.py
armada_sde/management/commands/pg_load_sde.py
armada_sde/management/commands/pg_move_sde.py
armada_sde/models/__init__.py
armada_sde/models/generated.py
armada_sde-0.3.0.dist-info/METADATA
armada_sde-0.3.0.dist-info/RECORD
armada_sde-0.3.0.dist-info/WHEEL
armada_sde-0.3.0.dist-info/top_level.txt
tests/testapp/__init__.py
tests/testapp/admin.py
tests/testapp/apps.py
tests/testapp/models.py
tests/testapp/tests.py
tests/testapp/urls.py
tests/testapp/views.py
tests/testapp/migrations/__init__.py
